rfr.py
rfr-0.1.3.dist-info/LICENSE
rfr-0.1.3.dist-info/METADATA
rfr-0.1.3.dist-info/WHEEL
rfr-0.1.3.dist-info/top_level.txt
rfr-0.1.3.dist-info/RECORD
