Metadata-Version: 2.1
Name: rfr
Version: 0.1.3
Summary: Python module that adds fast resume data to torrent files to be used by rtorrent
Home-page: https://github.com/brbaird/rfr
Author: Braden Baird
Author-email: bradenbdev@gmail.com
License: GPLv3
Platform: UNKNOWN
Classifier: Development Status :: 2 - Pre-Alpha
Classifier: Programming Language :: Python :: 3
Classifier: Intended Audience :: Developers
Classifier: License :: OSI Approved :: GNU General Public License v3 (GPLv3)
Classifier: Topic :: Software Development :: Libraries
Classifier: Topic :: Utilities
Requires-Python: >=3.4.0
License-File: LICENSE
Requires-Dist: bencode.py
